Workbook

Sheet Premissas
B2: PRANCHA — Premissas de economia (inputs em azul)
B4: Parâmetro | C4: Valor | D4: Unidade | E4: Notas
B5: Custo madeira | C5: 420 | D5: R$/m | E5: Escoramento / barra leve
B6: Custo aço estrutural | C6: 1860 | D6: R$/m | E6: Perfil I / treliça
B7: Custo concreto | C7: 980 | D7: R$/m | E7: Equivalente de seção de tabuleiro/pilar
B8: Custo cabo | C8: 1240 | D8: R$/m | E8: Somente tração
B9: Custo apoio elastomérico | C9: 8500 | D9: R$/un | E9: Permite rotação
B10: Custo encontro extra | C10: 28000 | D10: R$/un | E10: Fundação adicional
B11: Resistência madeira (rel) | C11: 0.35 | D11: adim. | E11: 1.00 = aço
B12: Resistência aço (rel) | C12: 1 | D12: adim. | E12: Referência
B13: Resistência concreto comp. | C13: 0.85 | D13: adim. | E13: Compressão
B14: Resistência concreto tração | C14: 0.12 | D14: adim. | E14: Sem armadura extra
B15: Resistência cabo tração | C15: 1.35 | D15: adim. | E15: Cabo não resiste compressão
B16: Peso madeira | C16: 0.4 | D16: adim. | E16: Relativo ao aço
B17: Peso aço | C17: 1 | D17: adim.
B18: Peso concreto | C18: 1.45 | D18: adim.
B19: Peso cabo | C19: 0.22 | D19: adim.
B20: FS alvo 3 estrelas | C20: 1.8 | D20: adim. | E20: Fator de segurança
B21: FS mínimo para passar | C21: 1.15 | D21: adim. | E21: Abaixo = colapso ou reprova
B22: Limite de flecha | C22: 800 | D22: L/x | E22: L/800
B23: Multiplicador orçamento folga | C23: 1.35 | D23: x | E23: Orçamento = custo ref. * isto
B24: Custo mão de obra | C24: 0.18 | D24: fração | E24: % sobre material
B26: Células amarelas / texto azul = inputs. Demais abas puxam estas premissas.

Sheet Materiais
B2: Catálogo de materiais — PRANCHA
B4: Material | C4: Custo (R$/m) | D4: Tração | E4: Compressão | F4: Peso rel. | G4: Uso típico | H4: Cor UI
B5: Madeira | C5: =Premissas!C5 -> 420 | D5: 0.25 | E5: =Premissas!C11 -> 0.35 | F5: =Premissas!C16 -> 0.4 | G5: Escora, banzo curto, teste inicial | H5: #B08968
B6: Aço estrutural | C6: =Premissas!C6 -> 1860 | D6: =Premissas!C12 -> 1 | E6: =Premissas!C12 -> 1 | F6: =Premissas!C17 -> 1 | G6: Treliça, viga, pilar | H6: #8A9AA8
B7: Concreto | C7: =Premissas!C7 -> 980 | D7: =Premissas!C14 -> 0.12 | E7: =Premissas!C13 -> 0.85 | F7: =Premissas!C18 -> 1.45 | G7: Pilar, tabuleiro, encontro | H7: #C4BBB2
B8: Cabo de aço | C8: =Premissas!C8 -> 1240 | D8: =Premissas!C15 -> 1.35 | E8: 0 | F8: =Premissas!C19 -> 0.22 | G8: Estai, suspensão, tirante | H8: #D9E2EC
B9: Apoio elastomérico | C9: =Premissas!C9 -> 8500 | D9: — | E9: — | F9: 0.15 | G9: Libera rotação no encontro | H9: #4A4A4A

Sheet Niveis
B2: Campanha — 24 obras (6 biomas × 4 níveis)
B4: ID | C4: Bioma | D4: Nome da obra | E4: Vão (m) | F4: Carga | G4: Restrição-mestre | H4: Orçamento (R$) | I4: FS 3★ | J4: Ensina | K4: Tutorial? | L4: Estrelas máx. ref.
B5: 1 | C5: Planície | D5: Córrego do Aprendiz | E5: 14 | F5: Van 3 t | G5: Nenhuma — só atravessar | H5: =E5*Materiais!C6*0.42*Premissas!C23 -> 14764.68 | I5: =Premissas!C20 -> 1.8 | J5: Nós, barras, testar | K5: Sim | L5: 3
B6: 2 | C6: Planície | D6: Ponte do Sítio | E6: 18 | F6: Caminhão 8 t | G6: Orçamento apertado | H6: =E6*Materiais!C6*0.42*Premissas!C23 -> 18983.16 | I6: =Premissas!C20 -> 1.8 | J6: Não overbuildar | K6: Sim | L6: 3
B7: 3 | C7: Planície | D7: Rio do Meio | E7: 24 | F7: Ônibus 12 t | G7: Cabo disponível | H7: =E7*Materiais!C6*0.42*Premissas!C23 -> 25310.88 | I7: =Premissas!C20 -> 1.8 | J7: Tração ≠ compressão | K7: Sim | L7: 3
B8: 4 | C8: Planície | D8: Passagem da Colheita | E8: 28 | F8: Bitrem 32 t | G8: Carga pesada lenta | H8: =E8*Materiais!C6*0.42*Premissas!C23 -> 29529.36 | I8: =Premissas!C20 -> 1.8 | J8: Carga móvel simples | K8: Não | L8: 3
B9: 5 | C9: Canyon | D9: Fenda Seca | E9: 32 | F9: Caminhão 12 t | G9: Encontros altos / flambagem | H9: =E9*Materiais!C6*0.5*Premissas!C23 -> 40176 | I9: =Premissas!C20 -> 1.8 | J9: Pilar esbelto | K9: Não | L9: 3
B10: 6 | C10: Canyon | D10: Vão do Gavião | E10: 38 | F10: Dois carros | G10: Pouco aço no canteiro | H10: =E10*Materiais!C6*0.5*Premissas!C23 -> 47709 | I10: =Premissas!C20 -> 1.8 | J10: Treliça eficiente | K10: Não | L10: 3
B11: 7 | C11: Canyon | D11: Corte da Pedra | E11: 42 | F11: Caminhão 16 t | G11: Proibido pilar no leito | H11: =E11*Materiais!C6*0.5*Premissas!C23 -> 52731 | I11: =Premissas!C20 -> 1.8 | J11: Vão livre obrigatório | K11: Não | L11: 3
B12: 8 | C12: Canyon | D12: Abismo Norte | E12: 48 | F12: Bitrem 36 t | G12: Orçamento + vão livre | H12: =E12*Materiais!C6*0.5*Premissas!C23 -> 60264 | I12: =Premissas!C20 -> 1.8 | J12: Duas restrições | K12: Não | L12: 3
B13: 9 | C13: Estuário | D13: Maré Baixa | E13: 26 | F13: Van + vento leve | G13: Nível d'água sobe no 2º teste | H13: =E13*Materiais!C6*0.55*Premissas!C23 -> 35907.3 | I13: =Premissas!C20 -> 1.8 | J13: Peso hidrostático | K13: Não | L13: 3
B14: 10 | C14: Estuário | D14: Canal do Porto | E14: 34 | F14: Caminhão 14 t | G14: Gabarito náutico 8 m | H14: =E14*Materiais!C6*0.55*Premissas!C23 -> 46955.7 | I14: =Premissas!C20 -> 1.8 | J14: Altura livre | K14: Não | L14: 3
B15: 11 | C15: Estuário | D15: Foz do Itajaí | E15: 40 | F15: Bitrem 40 t | G15: Gabarito 10 m + maré | H15: =E15*Materiais!C6*0.55*Premissas!C23 -> 55242 | I15: =Premissas!C20 -> 1.8 | J15: Combo ambiental | K15: Não | L15: 3
B16: 12 | C16: Estuário | D16: Porto Noturno | E16: 44 | F16: Duas cargas opostas | G16: Tráfego simultâneo | H16: =E16*Materiais!C6*0.55*Premissas!C23 -> 60766.2 | I16: =Premissas!C20 -> 1.8 | J16: Momentos invertidos | K16: Não | L16: 3
B17: 13 | C17: Serra | D17: Camada de Vento | E17: 30 | F17: Ônibus 14 t | G17: Vento 70 km/h | H17: =E17*Materiais!C6*0.58*Premissas!C23 -> 43691.4 | I17: =Premissas!C20 -> 1.8 | J17: Contra-ventamento | K17: Não | L17: 3
B18: 14 | C18: Serra | D18: Serra do Rio do Rastro | E18: 36 | F18: Caminhão 16 t | G18: Vento 90 km/h | H18: =E18*Materiais!C6*0.58*Premissas!C23 -> 52429.68 | I18: =Premissas!C20 -> 1.8 | J18: Cabos + rigidez lateral | K18: Não | L18: 3
B19: 15 | C19: Serra | D19: Pico do Corcovado SC | E19: 40 | F19: Van + vento rajada | G19: Rajadas no ensaio | H19: =E19*Materiais!C6*0.58*Premissas!C23 -> 58255.2 | I19: =Premissas!C20 -> 1.8 | J19: Carga variável no tempo | K19: Não | L19: 3
B20: 16 | C20: Serra | D20: Passagem Austral | E20: 46 | F20: Bitrem 36 t | G20: Vento + orçamento | H20: =E20*Materiais!C6*0.58*Premissas!C23 -> 66993.48 | I20: =Premissas!C20 -> 1.8 | J20: Boss do bioma | K20: Não | L20: 3
B21: 17 | C21: Mangue | D21: Solo Mole I | E21: 22 | F21: Caminhão 10 t | G21: Fundação cara | H21: =E21*Materiais!C6*0.62*Premissas!C23 -> 34250.04 | I21: =Premissas!C20 -> 1.8 | J21: Poucos pilares | K21: Não | L21: 3
B22: 18 | C22: Mangue | D22: Estrada da Vila | E22: 28 | F22: Ônibus 12 t | G22: Recalque diferencial | H22: =E22*Materiais!C6*0.62*Premissas!C23 -> 43590.96 | I22: =Premissas!C20 -> 1.8 | J22: Apoios flexíveis | K22: Não | L22: 3
B23: 19 | C23: Mangue | D23: Canal do Siri | E23: 34 | F23: Bitrem 28 t | G23: Proibido encontro no mangue D | H23: =E23*Materiais!C6*0.62*Premissas!C23 -> 52931.88 | I23: =Premissas!C20 -> 1.8 | J23: Vão assimétrico | K23: Não | L23: 3
B24: 20 | C24: Mangue | D24: Baía Enterrada | E24: 40 | F24: Caminhão 18 t | G24: Solo + maré | H24: =E24*Materiais!C6*0.62*Premissas!C23 -> 62272.8 | I24: =Premissas!C20 -> 1.8 | J24: Combo solo/água | K24: Não | L24: 3
B25: 21 | C25: Urbano | D25: Linha do Metrô | E25: 24 | F25: Metrô 80 t eq. | G25: Gabarito ferroviário | H25: =E25*Materiais!C6*0.7*Premissas!C23 -> 42184.8 | I25: =Premissas!C20 -> 1.8 | J25: Flecha rigorosa | K25: Não | L25: 3
B26: 22 | C26: Urbano | D26: Obra em Etapas | E26: 30 | F26: Caminhão 16 t | G26: Escorar → concretar → tirar escora | H26: =E26*Materiais!C6*0.7*Premissas!C23 -> 52731 | I26: =Premissas!C20 -> 1.8 | J26: Peso construtivo | K26: Não | L26: 3
B27: 23 | C27: Urbano | D27: Patrimônio Centro | E27: 36 | F27: Ônibus 14 t | G27: Não demolir arco existente | H27: =E27*Materiais!C6*0.7*Premissas!C23 -> 63277.2 | I27: =Premissas!C20 -> 1.8 | J27: Reforço | K27: Não | L27: 3
B28: 24 | C28: Urbano | D28: Hercílio Luz — Set-piece | E28: 52 | F28: Trem turístico 28 t | G28: Vento 90 + gabarito 18 + patrimônio | H28: =E28*Materiais!C6*0.7*Premissas!C23 -> 91400.4 | I28: =Premissas!C20 -> 1.8 | J28: Boss final | K28: Não | L28: 3
B48: Orçamento = Vão × Custo do aço × fator de bioma × folga (Premissas!C23). Vão é input azul.

Sheet Estrelas
B2: Regra das 3 estrelas
B4: Estrela | C4: Condição | D4: Feedback no relatório
B5: ★☆☆ | C5: Veículo atravessa e a estrutura não colapsa (FS ≥ FS mínimo). | D5: APROVADO — estrutura em serviço
B6: ★★☆ | C6: Custo total ≤ orçamento da obra. | D6: DENTRO DO TETO — gestão ok
B7: ★★★ | C7: FS ≥ FS alvo 3★ OU custo ≤ 80% do orçamento. | D7: SOLUÇÃO ELEGANTE — ART com elogio
B9: Reprovado: colapso, veículo cai, flecha > L/limite, ou violação de gabarito/vento fatal.

Sheet Tutorial
B2: Script do tutorial (obras 01–03)
B4: Passo | C4: Obra | D4: O que o jogo mostra | E4: O que o jogador faz
B5: 1 | C5: 01 | D5: "O vão não perdoa. Comece pelos nós." | E5: Clicar encontro E e arrastar até D.
B6: 2 | C6: 01 | D6: Snap magnético + cota em metros. | E6: Soltar a primeira barra de madeira.
B7: 3 | C7: 01 | D7: Botão TESTAR CARGA pulsa. | E7: Rodar o ensaio da van 3 t.
B8: 4 | C8: 01 | D8: Barras ficam verdes. 1 estrela. | E8: Avançar mesmo sem otimizar.
B9: 5 | C9: 02 | D9: Orçamento aparece em R$ e desce a cada metro. | E9: Reconstruir mais barato.
B10: 6 | C10: 02 | D10: Treliça simples é sugerida por uma nota de canteiro. | E10: Descobrir triangulação.
B11: 7 | C11: 03 | D11: Cabo entra no catálogo. Tooltip: só tração. | E11: Usar cabo no banzo inferior ou estai.
B12: 8 | C12: 03 | D12: Se o cabo flambar visualmente (empurra), ele folga. | E12: Corrigir e ganhar 3ª estrela.
